ue3_template/2_comparator/src/comparator.vhd
library ieee; use ieee.std_logic_1164.all;
entity fa is
  port(a,b,cin: in std_ulogic;
       cout, s: out std_ulogic);
end;

library ieee; use ieee.std_logic_1164.all;
entity adder is
  port(a,b:  in std_ulogic_vector(7 downto 0);
       cin:  in std_ulogic;
       cout: out std_ulogic;
       sum:  out std_ulogic_vector(7 downto 0));
end;

library ieee; use ieee.std_logic_1164.all;
entity comparator is
  port(a, b: in std_ulogic_vector(7 downto 0);
       result: out std_ulogic_vector(1 downto 0));
end;



--TODO implement architectures
architecture struct of fa is
begin
    cout <= (a and b) or (a and cin) or (b and cin);
    s <= a xor b xor cin;
end;

architecture struct of adder is
  component fa 
        port(a, b, cin: in std_ulogic;
            cout, s: out std_ulogic);
  end component;
  signal c0, c1, c2, c3, c4, c5, c6: std_ulogic;
begin
  fa0: fa port map(a(0), b(0), cin, c0, sum(0));
  fa1: fa port map(a(1), b(1), c0, c1, sum(1));
  fa2: fa port map(a(2), b(2), c1, c2, sum(2));
  fa3: fa port map(a(3), b(3), c2, c3, sum(3));
  fa4: fa port map(a(4), b(4), c3, c4, sum(4));
  fa5: fa port map(a(5), b(5), c4, c5, sum(5));
  fa6: fa port map(a(6), b(6), c5, c6, sum(6));
  fa7: fa port map(a(7), b(7), c6, cout, sum(7));
end;

architecture struct of comparator is
  component adder is
    port(a,b:  in std_ulogic_vector(7 downto 0);
        cin:  in std_ulogic;
        cout: out std_ulogic;
        sum:  out std_ulogic_vector(7 downto 0));
  end component;

  signal b_inv: std_ulogic_vector(7 downto 0);
  signal diff: std_ulogic_vector(7 downto 0);
  signal cout: std_ulogic;
  signal or01, or23, or45, or67: std_ulogic;
  signal or0123, or4567: std_ulogic;
  signal or012345678: std_ulogic;
begin
  b_inv <= not b;
  sub0: adder port map(a => a, b => b_inv, cin => '1', cout => cout, sum => diff);

  or01 <= diff(0) or diff(1);
  or23 <= diff(2) or diff(3);
  or45 <= diff(4) or diff(5);
  or67 <= diff(6) or diff(7);
  or0123 <= or01 or or23;
  or4567 <= or45 or or67;
  or012345678 <= or0123 or or4567;

  result(0) <= not cout;
  result(1) <= cout and or012345678;
end;

ue3_template/2_comparator/tb/testbench.vhd
-- Testbench

library ieee; use ieee.std_logic_1164.all; use ieee.std_logic_unsigned.all; use ieee.numeric_std.all;

entity testbench is
end;

architecture test of testbench is
  component comparator
    port(a, b:   in std_ulogic_vector(7 downto 0);
         result: out std_ulogic_vector(1 downto 0));
  end component;
  signal a, b:    std_ulogic_vector(7 downto 0);
  signal y:  std_ulogic_vector(1 downto 0);
begin
  my_comparator: comparator port map(a, b, y);
  
  process begin
    a <= std_ulogic_vector(to_unsigned(15, a'length));
    b <= std_ulogic_vector(to_unsigned(15, b'length));
    wait for 5 ns;
    report "comp(15, 15) = " & integer'image(to_integer(unsigned(y)));
    
    a <= std_ulogic_vector(to_unsigned(3, a'length));
    b <= std_ulogic_vector(to_unsigned(15, b'length));
    wait for 5 ns;
    report "comp(3, 15) = " & integer'image(to_integer(unsigned(y))); 

    a <= std_ulogic_vector(to_unsigned(15, a'length));
    b <= std_ulogic_vector(to_unsigned(3, b'length));
    wait for 5 ns;
    report "comp(15, 3) = " & integer'image(to_integer(unsigned(y))); 

    report "-----------------";
    
    for aa in 0 to 127 loop
      for bb in 0 to 127 loop
        a <= std_ulogic_vector(to_unsigned(aa, a'length));
        b <= std_ulogic_vector(to_unsigned(bb, b'length));			
        wait for 5 ns;
        if (aa = bb) and (y /= "00") then 
          report "comp(" & integer'image(aa) & ", " & integer'image(bb) & ") = " & integer'image(to_integer(unsigned(y))) & ", should be 0" severity error; 
          wait;
        elsif (aa < bb) and (y /= "01") then 
          report "comp(" & integer'image(aa) & ", " & integer'image(bb) & ") = " & integer'image(to_integer(unsigned(y))) & ", should be 1" severity error; 
          wait;
        elsif (aa > bb ) and (y /= "10") then
          report "comp(" & integer'image(aa) & ", " & integer'image(bb) & ") = " & integer'image(to_integer(unsigned(y))) & ", should be 2" severity error; 
          wait;
        end if;
        wait for 5 ns;
      end loop;
    end loop;
    report "No failure found.";
    wait;
  end process;
end;

ue3_template/2_comparator/sim/result.vcd
$date
  Sun Apr 12 16:10:30 2026
$end
$version
  GHDL v0
$end
$timescale
  1 fs
$end
$scope module standard $end
$upscope $end
$scope module textio $end
$upscope $end
$scope module std_logic_1164 $end
$upscope $end
$scope module std_logic_arith $end
$upscope $end
$scope module std_logic_unsigned $end
$upscope $end
$scope module numeric_std $end
$upscope $end
$scope module testbench $end
$var reg 8 ! a[7:0] $end
$var reg 8 " b[7:0] $end
$var reg 2 # y[1:0] $end
$scope module my_comparator $end
$var reg 8 $ a[7:0] $end
$var reg 8 % b[7:0] $end
$var reg 2 & result[1:0] $end
$var reg 8 ' b_inv[7:0] $end
$var reg 8 ( diff[7:0] $end
$var reg 1 ) cout $end
$var reg 1 * or01 $end
$var reg 1 + or23 $end
$var reg 1 , or45 $end
$var reg 1 - or67 $end
$var reg 1 . or0123 $end
$var reg 1 / or4567 $end
$var reg 1 0 or012345678 $end
$scope module sub0 $end
$var reg 8 1 a[7:0] $end
$var reg 8 2 b[7:0] $end
$var reg 1 3 cin $end
$var reg 1 4 cout $end
$var reg 8 5 sum[7:0] $end
$var reg 1 6 c0 $end
$var reg 1 7 c1 $end
$var reg 1 8 c2 $end
$var reg 1 9 c3 $end
$var reg 1 : c4 $end
$var reg 1 ; c5 $end
$var reg 1 < c6 $end
$scope module fa0 $end
$var reg 1 = a $end
$var reg 1 > b $end
$var reg 1 ? cin $end
$var reg 1 @ cout $end
$var reg 1 A s $end
$upscope $end
$scope module fa1 $end
$var reg 1 B a $end
$var reg 1 C b $end
$var reg 1 D cin $end
$var reg 1 E cout $end
$var reg 1 F s $end
$upscope $end
$scope module fa2 $end
$var reg 1 G a $end
$var reg 1 H b $end
$var reg 1 I cin $end
$var reg 1 J cout $end
$var reg 1 K s $end
$upscope $end
$scope module fa3 $end
$var reg 1 L a $end
$var reg 1 M b $end
$var reg 1 N cin $end
$var reg 1 O cout $end
$var reg 1 P s $end
$upscope $end
$scope module fa4 $end
$var reg 1 Q a $end
$var reg 1 R b $end
$var reg 1 S cin $end
$var reg 1 T cout $end
$var reg 1 U s $end
$upscope $end
$scope module fa5 $end
$var reg 1 V a $end
$var reg 1 W b $end
$var reg 1 X cin $end
$var reg 1 Y cout $end
$var reg 1 Z s $end
$upscope $end
$scope module fa6 $end
$var reg 1 [ a $end
$var reg 1 \ b $end
$var reg 1 ] cin $end
$var reg 1 ^ cout $end
$var reg 1 _ s $end
$upscope $end
$scope module fa7 $end
$var reg 1 ` a $end
$var reg 1 a b $end
$var reg 1 b cin $end
$var reg 1 c cout $end
$var reg 1 d s $end
$upscope $end
$upscope $end
$upscope $end
$upscope $end
$enddefinitions $end
#0
b00001111 !
b00001111 "
b00 #
b00001111 $
b00001111 %
b00 &
b11110000 '
b00000000 (
1)
0*
0+
0,
0-
0.
0/
00
b00001111 1
b11110000 2
13
14
b00000000 5
16
17
18
19
1:
1;
1<
1=
0>
1?
1@
0A
1B
0C
1D
1E
0F
1G
0H
1I
1J
0K
1L
0M
1N
1O
0P
0Q
1R
1S
1T
0U
0V
1W
1X
1Y
0Z
0[
1\
1]
1^
0_
0`
1a
1b
1c
0d
#5000000
b00000011 !
b01 #
b00000011 $
b01 &
b11110100 (
0)
1+
1,
1-
1.
1/
10
b00000011 1
04
b11110100 5
08
09
0:
0;
0<
0G
0J
1K
0L
0N
0O
0P
0S
0T
1U
0X
0Y
1Z
0]
0^
1_
0b
0c
1d
#10000000
b00001111 !
b00000011 "
b10 #
b00001111 $
b00000011 %
b10 &
b11111100 '
b00001100 (
1)
0,
0-
0/
b00001111 1
b11111100 2
14
b00001100 5
18
19
1:
1;
1<
1G
1H
1J
1K
1L
1M
1N
1O
1P
1S
1T
0U
1X
1Y
0Z
1]
1^
0_
1b
1c
0d
#15000000
b00000000 !
b00000000 "
b00 #
b00000000 $
b00000000 %
b00 &
b11111111 '
b00000000 (
1)
0*
0+
0,
0-
0.
0/
00
b00000000 1
b11111111 2
14
b00000000 5
16
17
18
19
1:
1;
1<
0=
1>
1@
0A
0B
1C
1D
1E
0F
0G
1I
1J
0K
0L
1N
1O
0P
1S
1T
0U
1X
1Y
0Z
1]
1^
0_
1b
1c
0d
#20000000
#25000000
b00000001 "
b01 #
b00000001 %
b01 &
b11111110 '
b11111111 (
0)
1*
1+
1,
1-
1.
1/
10
b11111110 2
04
b11111111 5
06
07
08
09
0:
0;
0<
0>
0@
1A
0D
0E
1F
0I
0J
1K
0N
0O
1P
0S
0T
1U
0X
0Y
1Z
0]
0^
1_
0b
0c
1d
#30000000
#35000000
b00000010 "
b00000010 %
b11111101 '
b11111110 (
1*
b11111101 2
b11111110 5
16
1>
1@
0A
0C
1D
1F
#40000000
#45000000
b00000011 "
b00000011 %
b11111100 '
b11111101 (
b11111100 2
b11111101 5
06
0>
0@
1A
0D
0F
#50000000
#55000000
b00000100 "
b00000100 %
b11111011 '
b11111100 (
0*
b11111011 2
b11111100 5
16
17
1>
1@
0A
1C
1D
1E
0F
0H
1I
1K
#60000000
#65000000
b00000101 "
b00000101 %
b11111010 '
b11111011 (
1*
b11111010 2
b11111011 5
06
07
0>
0@
1A
0D
0E
1F
0I
0K
#70000000
#75000000
b00000110 "
b00000110 %
b11111001 '
b11111010 (
1*
b11111001 2
b11111010 5
16
1>
1@
0A
0C
1D
1F
#80000000
#85000000
b00000111 "
b00000111 %
b11111000 '
b11111001 (
b11111000 2
b11111001 5
06
0>
0@
1A
0D
0F
#90000000
#95000000
b00001000 "
b00001000 %
b11110111 '
b11111000 (
0*
1+
1.
b11110111 2
b11111000 5
16
17
18
1>
1@
0A
1C
1D
1E
0F
1H
1I
1J
0K
0M
1N
1P
#100000000
#105000000
b00001001 "
b00001001 %
b11110110 '
b11110111 (
1*
b11110110 2
b11110111 5
06
07
08
0>
0@
1A
0D
0E
1F
0I
0J
1K
0N
0P
#110000000
#115000000
b00001010 "
b00001010 %
b11110101 '
b11110110 (
1*
b11110101 2
b11110110 5
16
1>
1@
0A
0C
1D
1F
#120000000
#125000000
b00001011 "
b00001011 %
b11110100 '
b11110101 (
b11110100 2
b11110101 5
06
0>
0@
1A
0D
0F
#130000000
#135000000
b00001100 "
b00001100 %
b11110011 '
b11110100 (
0*
1+
1.
b11110011 2
b11110100 5
16
17
1>
1@
0A
1C
1D
1E
0F
0H
1I
1K
#140000000
#145000000
b00001101 "
b00001101 %
b11110010 '
b11110011 (
1*
0+
b11110010 2
b11110011 5
06
07
0>
0@
1A
0D
0E
1F
0I
0K
#150000000
#155000000
b00001110 "
b00001110 %
b11110001 '
b11110010 (
1*
1.
b11110001 2
b11110010 5
16
1>
1@
0A
0C
1D
1F
#160000000
#165000000
b00001111 "
b00001111 %
b11110000 '
b11110001 (
b11110000 2
b11110001 5
06
0>
0@
1A
0D
0F
#170000000
#175000000
b00010000 "
b00010000 %
b11101111 '
b11110000 (
0*
0+
0.
b11101111 2
b11110000 5
16
17
18
19
1>
1@
0A
1C
1D
1E
0F
1H
1I
1J
0K
1M
1N
1O
0P
0R
1S
1U
#180000000
#185000000
b00010001 "
b00010001 %
b11101110 '
b11101111 (
1*
1+
1.
b11101110 2
b11101111 5
06
07
08
09
0>
0@
1A
0D
0E
1F
0I
0J
1K
0N
0O
1P
0S
0U
#190000000
#195000000
b00010010 "
b00010010 %
b11101101 '
b11101110 (
1*
b11101101 2
b11101110 5
16
1>
1@
0A
0C
1D
1F
#200000000
#205000000
b00010011 "
b00010011 %
b11101100 '
b11101101 (
b11101100 2
b11101101 5
06
0>
0@
1A
0D
0F
#210000000
#215000000
b00010100 "
b00010100 %
b11101011 '
b11101100 (
0*
b11101011 2
b11101100 5
16
17
1>
1@
0A
1C
1D
1E
0F
0H
1I
1K
#220000000
#225000000
b00010101 "
b00010101 %
b11101010 '
b11101011 (
1*
b11101010 2
b11101011 5
06
07
0>
0@
1A
0D
0E
1F
0I
0K
#230000000
#235000000
b00010110 "
b00010110 %
b11101001 '
b11101010 (
1*
b11101001 2
b11101010 5
16
1>
1@
0A
0C
1D
1F
#240000000
#245000000
b00010111 "
b00010111 %
b11101000 '
b11101001 (
b11101000 2
b11101001 5
06
0>
0@
1A
0D
0F
#250000000
#255000000
b00011000 "
b00011000 %
b11100111 '
b11101000 (
0*
1+
1.
b11100111 2
b11101000 5
16
17
18
1>
1@
0A
1C
1D
1E
0F
1H
1I
1J
0K
0M
1N
1P
#260000000
#265000000
b00011001 "
b00011001 %
b11100110 '
b11100111 (
1*
b11100110 2
b11100111 5
06
07
08
0>
0@
1A
0D
0E
1F
0I
0J
1K
0N
0P
#270000000
#275000000
b00011010 "
b00011010 %
b11100101 '
b11100110 (
1*
b11100101 2
b11100110 5
16
1>
1@
0A
0C
1D
1F
#280000000
#285000000
b00011011 "
b00011011 %
b11100100 '
b11100101 (
b11100100 2
b11100101 5
06
0>
0@
1A
0D
0F
#290000000
#295000000
b00011100 "
b00011100 %
b11100011 '
b11100100 (
0*
1+
1.
b11100011 2
b11100100 5
16
17
1>
1@
0A
1C
1D
1E
0F
0H
1I
1K
#300000000
#305000000
b00011101 "
b00011101 %
b11100010 '
b11100011 (
1*
0+
b11100010 2
b11100011 5
06
07
0>
0@
1A
0D
0E
1F
0I
0K
#310000000
#315000000
b00011110 "
b00011110 %
b11100001 '
b11100010 (
1*
1.
b11100001 2
b11100010 5
16
1>
1@
0A
0C
1D
1F
#320000000
#325000000
b00011111 "
b00011111 %
b11100000 '
b11100001 (
b11100000 2
b11100001 5
06
0>
0@
1A
0D
0F
#330000000
#335000000
b00100000 "
b00100000 %
b11011111 '
b11100000 (
0*
0+
1,
0.
b11011111 2
b11100000 5
16
17
18
19
1:
1>
1@
0A
1C
1D
1E
0F
1H
1I
1J
0K
1M
1N
1O
0P
1R
1S
1T
0U
0W
1X
1Z
#340000000
#345000000
b00100001 "
b00100001 %
b11011110 '
b11011111 (
1*
1+
1.
b11011110 2
b11011111 5
06
07
08
09
0:
0>
0@
1A
0D
0E
1F
0I
0J
1K
0N
0O
1P
0S
0T
1U
0X
0Z
#350000000
#355000000
b00100010 "
b00100010 %
b11011101 '
b11011110 (
1*
b11011101 2
b11011110 5
16
1>
1@
0A
0C
1D
1F
#360000000
#365000000
b00100011 "
b00100011 %
b11011100 '
b11011101 (
b11011100 2
b11011101 5
06
0>
0@
1A
0D
0F
#370000000
#375000000
b00100100 "
b00100100 %
b11011011 '
b11011100 (
0*
b11011011 2
b11011100 5
16
17
1>
1@
0A
1C
1D
1E
0F
0H
1I
1K
#380000000
#385000000
b00100101 "
b00100101 %
b11011010 '
b11011011 (
1*
b11011010 2
b11011011 5
06
07
0>
0@
1A
0D
0E
1F
0I
0K
#390000000
#395000000
b00100110 "
b00100110 %
b11011001 '
b11011010 (
1*
b11011001 2
b11011010 5
16
1>
1@
0A
0C
1D
1F
#400000000
#405000000
b00100111 "
b00100111 %
b11011000 '
b11011001 (
b11011000 2
b11011001 5
06
0>
0@
1A
0D
0F
#410000000
#415000000
b00101000 "
b00101000 %
b11010111 '
b11011000 (
0*
1+
1.
b11010111 2
b11011000 5
16
17
18
1>
1@
0A
1C
1D
1E
0F
1H
1I
1J
0K
0M
1N
1P
#420000000
#425000000
b00101001 "
b00101001 %
b11010110 '
b11010111 (
1*
b11010110 2
b11010111 5
06
07
08
0>
0@
1A
0D
0E
1F
0I
0J
1K
0N
0P
#430000000
#435000000
b00101010 "
b00101010 %
b11010101 '
b11010110 (
1*
b11010101 2
b11010110 5
16
1>
1@
0A
0C
1D
1F
#440000000
#445000000
b00101011 "
b00101011 %
b11010100 '
b11010101 (
b11010100 2
b11010101 5
06
0>
0@
1A
0D
0F
#450000000
#455000000
b00101100 "
b00101100 %
b11010011 '
b11010100 (
0*
1+
1.
b11010011 2
b11010100 5
16
17
1>
1@
0A
1C
1D
1E
0F
0H
1I
1K
#460000000
#465000000
b00101101 "
b00101101 %
b11010010 '
b11010011 (
1*
0+
b11010010 2
b11010011 5
06
07
0>
0@
1A
0D
0E
1F
0I
0K
#470000000
#475000000
b00101110 "
b00101110 %
b11010001 '
b11010010 (
1*
1.
b11010001 2
b11010010 5
16
1>
1@
0A
0C
1D
1F
#480000000
#485000000
b00101111 "
b00101111 %
b11010000 '
b11010001 (
b11010000 2
b11010001 5
06
0>
0@
1A
0D
0F
#490000000
#495000000
b00110000 "
b00110000 %
b11001111 '
b11010000 (
0*
0+
1,
0.
b11001111 2
b11010000 5
16
17
18
19
1>
1@
0A
1C
1D
1E
0F
1H
1I
1J
0K
1M
1N
1O
0P
0R
1S
1U
#500000000
#505000000
b00110001 "
b00110001 %
b11001110 '
b11001111 (
1*
1+
0,
1.
b11001110 2
b11001111 5
06
07
08
09
0>
0@
1A
0D
0E
1F
0I
0J
1K
0N
0O
1P
0S
0U
#510000000
#515000000
b00110010 "
b00110010 %
b11001101 '
b11001110 (
1*
b11001101 2
b11001110 5
16
1>
1@
0A
0C
1D
1F
#520000000
#525000000
b00110011 "
b00110011 %
b11001100 '
b11001101 (
b11001100 2
b11001101 5
06
0>
0@
1A
0D
0F
#530000000
#535000000
b00110100 "
b00110100 %
b11001011 '
b11001100 (
0*
b11001011 2
b11001100 5
16
17
1>
1@
0A
1C
1D
1E
0F
0H
1I
1K
#540000000
#545000000
b00110101 "
b00110101 %
b11001010 '
b11001011 (
1*
b11001010 2
b11001011 5
06
07
0>
0@
1A
0D
0E
1F
0I
0K
#550000000
#555000000
b00110110 "
b00110110 %
b11001001 '
b11001010 (
1*
b11001001 2
b11001010 5
16
1>
1@
0A
0C
1D
1F
#560000000
#565000000
b00110111 "
b00110111 %
b11001000 '
b11001001 (
b11001000 2
b11001001 5
06
0>
0@
1A
0D
0F
#570000000
#575000000
b00111000 "
b00111000 %
b11000111 '
b11001000 (
0*
1+
1.
b11000111 2
b11001000 5
16
17
18
1>
1@
0A
1C
1D
1E
0F
1H
1I
1J
0K
0M
1N
1P
#580000000
#585000000
b00111001 "
b00111001 %
b11000110 '
b11000111 (
1*
b11000110 2
b11000111 5
06
07
08
0>
0@
1A
0D
0E
1F
0I
0J
1K
0N
0P
#590000000
#595000000
b00111010 "
b00111010 %
b11000101 '
b11000110 (
1*
b11000101 2
b11000110 5
16
1>
1@
0A
0C
1D
1F
#600000000
#605000000
b00111011 "
b00111011 %
b11000100 '
b11000101 (
b11000100 2
b11000101 5
06
0>
0@
1A
0D
0F
#610000000
#615000000
b00111100 "
b00111100 %
b11000011 '
b11000100 (
0*
1+
1.
b11000011 2
b11000100 5
16
17
1>
1@
0A
1C
1D
1E
0F
0H
1I
1K
#620000000
#625000000
b00111101 "
b00111101 %
b11000010 '
b11000011 (
1*
0+
b11000010 2
b11000011 5
06
07
0>
0@
1A
0D
0E
1F
0I
0K
#630000000
#635000000
b00111110 "
b00111110 %
b11000001 '
b11000010 (
1*
1.
b11000001 2
b11000010 5
16
1>
1@
0A
0C
1D
1F
#640000000
#645000000
b00111111 "
b00111111 %
b11000000 '
b11000001 (
b11000000 2
b11000001 5
06
0>
0@
1A
0D
0F
#650000000
#655000000
b01000000 "
b01000000 %
b10111111 '
b11000000 (
0*
0+
0,
0.
b10111111 2
b11000000 5
16
17
18
19
1:
1;
1>
1@
0A
1C
1D
1E
0F
1H
1I
1J
0K
1M
1N
1O
0P
1R
1S
1T
0U
1W
1X
1Y
0Z
0\
1]
1_
#660000000
#665000000
b01000001 "
b01000001 %
b10111110 '
b10111111 (
1*
1+
1,
1.
b10111110 2
b10111111 5
06
07
08
09
0:
0;
0>
0@
1A
0D
0E
1F
0I
0J
1K
0N
0O
1P
0S
0T
1U
0X
0Y
1Z
0]
0_
#670000000
#675000000
b01000010 "
b01000010 %
b10111101 '
b10111110 (
1*
b10111101 2
b10111110 5
16
1>
1@
0A
0C
1D
1F
#680000000
#685000000
b01000011 "
b01000011 %
b10111100 '
b10111101 (
b10111100 2
b10111101 5
06
0>
0@
1A
0D
0F
#690000000
#695000000
b01000100 "
b01000100 %
b10111011 '
b10111100 (
0*
b10111011 2
b10111100 5
16
17
1>
1@
0A
1C
1D
1E
0F
0H
1I
1K
#700000000
#705000000
b01000101 "
b01000101 %
b10111010 '
b10111011 (
1*
b10111010 2
b10111011 5
06
07
0>
0@
1A
0D
0E
1F
0I
0K
#710000000
#715000000
b01000110 "
b01000110 %
b10111001 '
b10111010 (
1*
b10111001 2
b10111010 5
16
1>
1@
0A
0C
1D
1F
#720000000
#725000000
b01000111 "
b01000111 %
b10111000 '
b10111001 (
b10111000 2
b10111001 5
06
0>
0@
1A
0D
0F
#730000000
#735000000
b01001000 "
b01001000 %
b10110111 '
b10111000 (
0*
1+
1.
b10110111 2
b10111000 5
16
17
18
1>
1@
0A
1C
1D
1E
0F
1H
1I
1J
0K
0M
1N
1P
#740000000
#745000000
b01001001 "
b01001001 %
b10110110 '
b10110111 (
1*
b10110110 2
b10110111 5
06
07
08
0>
0@
1A
0D
0E
1F
0I
0J
1K
0N
0P
#750000000
#755000000
b01001010 "
b01001010 %
b10110101 '
b10110110 (
1*
b10110101 2
b10110110 5
16
1>
1@
0A
0C
1D
1F
#760000000
#765000000
b01001011 "
b01001011 %
b10110100 '
b10110101 (
b10110100 2
b10110101 5
06
0>
0@
1A
0D
0F
#770000000
#775000000
b01001100 "
b01001100 %
b10110011 '
b10110100 (
0*
1+
1.
b10110011 2
b10110100 5
16
17
1>
1@
0A
1C
1D
1E
0F
0H
1I
1K
#780000000
#785000000
b01001101 "
b01001101 %
b10110010 '
b10110011 (
1*
0+
b10110010 2
b10110011 5
06
07
0>
0@
1A
0D
0E
1F
0I
0K
#790000000
#795000000
b01001110 "
b01001110 %
b10110001 '
b10110010 (
1*
1.
b10110001 2
b10110010 5
16
1>
1@
0A
0C
1D
1F
#800000000
#805000000
b01001111 "
b01001111 %
b10110000 '
b10110001 (
b10110000 2
b10110001 5
06
0>
0@
1A
0D
0F
#810000000
#815000000
b01010000 "
b01010000 %
b10101111 '
b10110000 (
0*
0+
0.
b10101111 2
b10110000 5
16
17
18
19
1>
1@
0A
1C
1D
1E
0F
1H
1I
1J
0K
1M
1N
1O
0P
0R
1S
1U
#820000000
#825000000
b01010001 "
b01010001 %
b10101110 '
b10101111 (
1*
1+
1.
b10101110 2
b10101111 5
06
07
08
09
0>
0@
1A
0D
0E
1F
0I
0J
1K
0N
0O
1P
0S
0U
#830000000
#835000000
b01010010 "
b01010010 %
b10101101 '
b10101110 (
1*
b10101101 2
b10101110 5
16
1>
1@
0A
0C
1D
1F
#840000000
#845000000
b01010011 "
b01010011 %
b10101100 '
b10101101 (
b10101100 2
b10101101 5
06
0>
0@
1A
0D
0F
#850000000
#855000000
b01010100 "
b01010100 %
b10101011 '
b10101100 (
0*
b10101011 2
b10101100 5
16
17
1>
1@
0A
1C
1D
1E
0F
0H
1I
1K
#860000000
#865000000
b01010101 "
b01010101 %
b10101010 '
b10101011 (
1*
b10101010 2
b10101011 5
06
07
0>
0@
1A
0D
0E
1F
0I
0K
#870000000
#875000000
b01010110 "
b01010110 %
b10101001 '
b10101010 (
1*
b10101001 2
b10101010 5
16
1>
1@
0A
0C
1D
1F
#880000000
#885000000
b01010111 "
b01010111 %
b10101000 '
b10101001 (
b10101000 2
b10101001 5
06
0>
0@
1A
0D
0F
#890000000
#895000000
b01011000 "
b01011000 %
b10100111 '
b10101000 (
0*
1+
1.
b10100111 2
b10101000 5
16
17
18
1>
1@
0A
1C
1D
1E
0F
1H
1I
1J
0K
0M
1N
1P
#900000000
#905000000
b01011001 "
b01011001 %
b10100110 '
b10100111 (
1*
b10100110 2
b10100111 5
06
07
08
0>
0@
1A
0D
0E
1F
0I
0J
1K
0N
0P
#910000000
#915000000
b01011010 "
b01011010 %
b10100101 '
b10100110 (
1*
b10100101 2
b10100110 5
16
1>
1@
0A
0C
1D
1F
#920000000
#925000000
b01011011 "
b01011011 %
b10100100 '
b10100101 (
b10100100 2
b10100101 5
06
0>
0@
1A
0D
0F
#930000000
#935000000
b01011100 "
b01011100 %
b10100011 '
b10100100 (
0*
1+
1.
b10100011 2
b10100100 5
16
17
1>
1@
0A
1C
1D
1E
0F
0H
1I
1K
#940000000
#945000000
b01011101 "
b01011101 %
b10100010 '
b10100011 (
1*
0+
b10100010 2
b10100011 5
06
07
0>
0@
1A
0D
0E
1F
0I
0K
#950000000
#955000000
b01011110 "
b01011110 %
b10100001 '
b10100010 (
1*
1.
b10100001 2
b10100010 5
16
1>
1@
0A
0C
1D
1F
#960000000
#965000000
b01011111 "
b01011111 %
b10100000 '
b10100001 (
b10100000 2
b10100001 5
06
0>
0@
1A
0D
0F
#970000000
#975000000
b01100000 "
b01100000 %
b10011111 '
b10100000 (
0*
0+
1,
0.
b10011111 2
b10100000 5
16
17
18
19
1:
1>
1@
0A
1C
1D
1E
0F
1H
1I
1J
0K
1M
1N
1O
0P
1R
1S
1T
0U
0W
1X
1Z
#980000000
#985000000
b01100001 "
b01100001 %
b10011110 '
b10011111 (
1*
1+
1.
b10011110 2
b10011111 5
06
07
08
09
0:
0>
0@
1A
0D
0E
1F
0I
0J
1K
0N
0O
1P
0S
0T
1U
0X
0Z
#990000000
#995000000
b01100010 "
b01100010 %
b10011101 '
b10011110 (
1*
b10011101 2
b10011110 5
16
1>
1@
0A
0C
1D
1F
#1000000000
#1005000000
b01100011 "
b01100011 %
b10011100 '
b10011101 (
b10011100 2
b10011101 5
06
0>
0@
1A
0D
0F
#1010000000
#1015000000
b01100100 "
b01100100 %
b10011011 '
b10011100 (
0*
b10011011 2
b10011100 5
16
17
1>
1@
0A
1C
1D
1E
0F
0H
1I
1K
#1020000000
#1025000000
b01100101 "
b01100101 %
b10011010 '
b10011011 (
1*
b10011010 2
b10011011 5
06
07
0>
0@
1A
0D
0E
1F
0I
0K
#1030000000
#1035000000
b01100110 "
b01100110 %
b10011001 '
b10011010 (
1*
b10011001 2
b10011010 5
16
1>
1@
0A
0C
1D
1F
#1040000000
#1045000000
b01100111 "
b01100111 %
b10011000 '
b10011001 (
b10011000 2
b10011001 5
06
0>
0@
1A
0D
0F
#1050000000
#1055000000
b01101000 "
b01101000 %
b10010111 '
b10011000 (
0*
1+
1.
b10010111 2
b10011000 5
16
17
18
1>
1@
0A
1C
1D
1E
0F
1H
1I
1J
0K
0M
1N
1P
#1060000000
#1065000000
b01101001 "
b01101001 %
b10010110 '
b10010111 (
1*
b10010110 2
b10010111 5
06
07
08
0>
0@
1A
0D
0E
1F
0I
0J
1K
0N
0P
#1070000000
#1075000000
b01101010 "
b01101010 %
b10010101 '
b10010110 (
1*
b10010101 2
b10010110 5
16
1>
1@
0A
0C
1D
1F
#1080000000
#1085000000
b01101011 "
b01101011 %
b10010100 '
b10010101 (
b10010100 2
b10010101 5
06
0>
0@
1A
0D
0F
#1090000000
#1095000000
b01101100 "
b01101100 %
b10010011 '
b10010100 (
0*
1+
1.
b10010011 2
b10010100 5
16
17
1>
1@
0A
1C
1D
1E
0F
0H
1I
1K
#1100000000
#1105000000
b01101101 "
b01101101 %
b10010010 '
b10010011 (
1*
0+
b10010010 2
b10010011 5
06
07
0>
0@
1A
0D
0E
1F
0I
0K
#1110000000
#1115000000
b01101110 "
b01101110 %
b10010001 '
b10010010 (
1*
1.
b10010001 2
b10010010 5
16
1>
1@
0A
0C
1D
1F
#1120000000
#1125000000
b01101111 "
b01101111 %
b10010000 '
b10010001 (
b10010000 2
b10010001 5
06
0>
0@
1A
0D
0F
#1130000000
#1135000000
b01110000 "
b01110000 %
b10001111 '
b10010000 (
0*
0+
1,
0.
b10001111 2
b10010000 5
16
17
18
19
1>
1@
0A
1C
1D
1E
0F
1H
1I
1J
0K
1M
1N
1O
0P
0R
1S
1U
#1140000000
#1145000000
b01110001 "
b01110001 %
b10001110 '
b10001111 (
1*
1+
0,
1.
b10001110 2
b10001111 5
06
07
08
09
0>
0@
1A
0D
0E
1F
0I
0J
1K
0N
0O
1P
0S
0U
#1150000000
#1155000000
b01110010 "
b01110010 %
b10001101 '
b10001110 (
1*
b10001101 2
b10001110 5
16
1>
1@
0A
0C
1D
1F
#1160000000
#1165000000
b01110011 "
b01110011 %
b10001100 '
b10001101 (
b10001100 2
b10001101 5
06
0>
0@
1A
0D
0F
#1170000000
#1175000000
b01110100 "
b01110100 %
b10001011 '
b10001100 (
0*
b10001011 2
b10001100 5
16
17
1>
1@
0A
1C
1D
1E
0F
0H
1I
1K
#1180000000
#1185000000
b01110101 "
b01110101 %
b10001010 '
b10001011 (
1*
b10001010 2
b10001011 5
06
07
0>
0@
1A
0D
0E
1F
0I
0K
#1190000000
#1195000000
b01110110 "
b01110110 %
b10001001 '
b10001010 (
1*
b10001001 2
b10001010 5
16
1>
1@
0A
0C
1D
1F
#1200000000
#1205000000
b01110111 "
b01110111 %
b10001000 '
b10001001 (
b10001000 2
b10001001 5
06
0>
0@
1A
0D
0F
#1210000000
#1215000000
b01111000 "
b01111000 %
b10000111 '
b10001000 (
0*
1+
1.
b10000111 2
b10001000 5
16
17
18
1>
1@
0A
1C
1D
1E
0F
1H
1I
1J
0K
0M
1N
1P
#1220000000
#1225000000
b01111001 "
b01111001 %
b10000110 '
b10000111 (
1*
b10000110 2
b10000111 5
06
07
08
0>
0@
1A
0D
0E
1F
0I
0J
1K
0N
0P
#1230000000
#1235000000
b01111010 "
b01111010 %
b10000101 '
b10000110 (
1*
b10000101 2
b10000110 5
16
1>
1@
0A
0C
1D
1F
#1240000000
#1245000000
b01111011 "
b01111011 %
b10000100 '
b10000101 (
b10000100 2
b10000101 5
06
0>
0@
1A
0D
0F
#1250000000
