ue4_template/1_countdown/src/ff_ea_bhv.vhd
library IEEE; 
use IEEE.STD_LOGIC_1164.all;
entity ff is
  generic(width: integer;
          reset_val: std_ulogic_vector(width-1 downto 0));
  port(clk, reset: in std_ulogic;
       d:          in std_ulogic_vector(width-1 downto 0);
       q:         out std_ulogic_vector(width-1 downto 0));
end;

architecture bhv of ff is
  
begin
  -- process is triggered everytime one of values in reset or clk changes
  process(reset, clk) begin
    if reset = '1' then
      q <= reset_val;
    elsif clk'event and clk = '1' then -- clk'event is true if clk changed
      q <= d;
    end if;
  end process;
end;


library IEEE; 
use IEEE.STD_LOGIC_1164.all;
entity ff_single is
  generic(reset_val: std_ulogic);
  port(clk, reset: in std_ulogic;
       d:          in std_ulogic;
       q:         out std_ulogic);
end;

architecture bhv of ff_single is
  
begin
  -- process is triggered everytime one of values in reset or clk changes
  process(reset, clk) begin
    if reset = '1' then
      q <= reset_val;
    elsif clk'event and clk = '1' then -- clk'event is true if clk changed
      q <= d;
    end if;
  end process;
end;

ue4_template/1_countdown/src/countdown_ea_struct.vhd
-- generic counter based on adder and register
library IEEE; 
use IEEE.STD_LOGIC_1164.all;

entity countdown is
  generic (width: integer);
  port(clk, reset: in  std_ulogic;
       y:          out std_ulogic_vector(width-1 downto 0);
       alarm:      out std_ulogic);
end;    

architecture struct of countdown is
  component ff is
  generic(width: integer;
          reset_val: std_ulogic_vector(width-1 downto 0));
  port(clk, reset: in std_ulogic;
       d:          in std_ulogic_vector(width-1 downto 0);
       q:         out std_ulogic_vector(width-1 downto 0));
  end component;

  component ff_single is
  generic(reset_val: std_ulogic);
  port(clk, reset: in std_ulogic;
       d:          in std_ulogic;
       q:         out std_ulogic);
  end component;

  signal curr_y: std_ulogic_vector(width-1 downto 0);
  signal next_y: std_ulogic_vector(width-1 downto 0);
  signal borrow: std_ulogic_vector(width-1 downto 0);
  signal or_chain: std_ulogic_vector(width-1 downto 0);
  signal zero_now: std_ulogic;
begin
  var_y: ff generic map (width => width, reset_val => (width-1 downto 0 => '1'))
        port map(clk => clk, reset => reset, d => next_y, q => curr_y);

  var_alarm: ff_single generic map (reset_val => '0')
                   port map (clk => clk, reset => reset, d => zero_now, q => alarm);

  y <= curr_y;
  borrow(0) <= '1';
  next_y(0) <= not curr_y(0);

  gen_sub: for i in 1 to width-1 generate
    borrow(i) <= borrow(i-1) and (not curr_y(i-1));
    next_y(i) <= curr_y(i) xor borrow(i);
    end generate;

  or_chain(0) <= curr_y(0);
  gen_or: for i in 1 to width-1 generate
      or_chain(i) <= or_chain(i-1) or curr_y(i);
    end generate;

    zero_now <= not or_chain(width-1);
end;

ue4_template/1_countdown/tb/testbench.vhd
library IEEE;
use IEEE.STD_LOGIC_1164.all;
use IEEE.STD_LOGIC_UNSIGNED.all; 
use IEEE.NUMERIC_STD.all;

entity testbench is
end;

architecture test of testbench is

  component countdown is
    generic(width: integer);
    port(clk, reset: in  std_ulogic;
         y:          out std_ulogic_vector(width-1 downto 0);
         alarm:      out std_ulogic);
  end component;

  constant w_a: integer := 3;
  constant w_b: integer := 4;  
    
  signal clk, reset: std_ulogic := '0';
  signal y_a:        std_ulogic_vector(w_a-1 downto 0);
  signal y_b:        std_ulogic_vector(w_b-1 downto 0);
  signal alarm_a:    std_ulogic;
  signal alarm_b:    std_ulogic;
  
begin
  -- initiate device to be tested
  four: countdown generic map(width => w_a) port map(clk, reset, y_a, alarm_a);
  five: countdown generic map(width => w_b) port map(clk, reset, y_b, alarm_b);
  
  -- generate clock with 10 ns period
  process
    variable a_ref : integer := 2**w_a-1;
    variable b_ref : integer := 2**w_b-1;
    variable alarm_a_ref, alarm_b_ref : std_ulogic := '0';
  begin
    
      for i in 1 to 35 loop
        clk <= not(clk);
        wait for 5 ps;
        clk <= not(clk);
        wait for 5 ps;
       
        report " y_a=" & integer'image(to_integer(unsigned(y_a))) & ", alarm = " & std_ulogic'image((alarm_a)) & "   |  y_b=" & integer'image(to_integer(unsigned(y_b))) & ", alarm = " & std_ulogic'image((alarm_b));
        assert to_integer(unsigned(y_a)) = a_ref report "Output for " & integer'image(w_a) & " bit width wrong: " & integer'image(to_integer(unsigned(y_a))) & " (should be " & integer'image(a_ref) & ")" severity failure;
        assert to_integer(unsigned(y_b)) = b_ref report "Output for " & integer'image(w_b) & " bit width wrong: " & integer'image(to_integer(unsigned(y_b))) & " (should be " & integer'image(b_ref) & ")" severity failure;
        assert alarm_a = alarm_a_ref report "Alarm for " & integer'image(w_a) & " is not triggered right: " & std_ulogic'image(alarm_a) & " (should be " & std_ulogic'image(alarm_a_ref) & ")" severity failure;
        assert alarm_b = alarm_b_ref report "Alarm for " & integer'image(w_b) & " is not triggered right: " & std_ulogic'image(alarm_b) & " (should be " & std_ulogic'image(alarm_b_ref) & ")" severity failure;
        if reset = '0' then
          if a_ref = 0 then
            a_ref := 2**w_a-1;
            alarm_a_ref := '1';
          else
            a_ref := a_ref - 1;
            alarm_a_ref := '0';
          end if;
          if b_ref = 0 then
            b_ref := 2**w_b-1;
            alarm_b_ref := '1';
          else
            b_ref := b_ref - 1;
            alarm_b_ref := '0';
          end if;
        end if;
      end loop;
      report "No failure found!";
      wait;
    end process;

    process begin
      report("reset");
      reset <= '1';
      wait for 24 ps;
      reset <= '0';
      report("reset released");
      wait;
   end process;
end;

ue4_template/1_countdown/sim/result.vcd
$date
  Sun Apr 26 14:42:41 2026
$end
$version
  GHDL v0
$end
$timescale
  1 fs
$end
$scope module standard $end
$upscope $end
$scope module textio $end
$upscope $end
$scope module std_logic_1164 $end
$upscope $end
$scope module std_logic_arith $end
$upscope $end
$scope module std_logic_unsigned $end
$upscope $end
$scope module numeric_std $end
$upscope $end
$scope module testbench $end
$var reg 1 ! clk $end
$var reg 1 " reset $end
$var reg 3 # y_a[2:0] $end
$var reg 4 $ y_b[3:0] $end
$var reg 1 % alarm_a $end
$var reg 1 & alarm_b $end
$scope module four $end
$var reg 1 ' clk $end
$var reg 1 ( reset $end
$var reg 3 ) y[2:0] $end
$var reg 1 * alarm $end
$var reg 3 + curr_y[2:0] $end
$var reg 3 , next_y[2:0] $end
$var reg 3 - borrow[2:0] $end
$var reg 3 . or_chain[2:0] $end
$var reg 1 / zero_now $end
$scope module var_y $end
$var reg 1 0 clk $end
$var reg 1 1 reset $end
$var reg 3 2 d[2:0] $end
$var reg 3 3 q[2:0] $end
$upscope $end
$scope module var_alarm $end
$var reg 1 4 clk $end
$var reg 1 5 reset $end
$var reg 1 6 d $end
$var reg 1 7 q $end
$upscope $end
$scope module gen_sub(1) $end
$upscope $end
$scope module gen_sub(2) $end
$upscope $end
$scope module gen_or(1) $end
$upscope $end
$scope module gen_or(2) $end
$upscope $end
$upscope $end
$scope module five $end
$var reg 1 8 clk $end
$var reg 1 9 reset $end
$var reg 4 : y[3:0] $end
$var reg 1 ; alarm $end
$var reg 4 < curr_y[3:0] $end
$var reg 4 = next_y[3:0] $end
$var reg 4 > borrow[3:0] $end
$var reg 4 ? or_chain[3:0] $end
$var reg 1 @ zero_now $end
$scope module var_y $end
$var reg 1 A clk $end
$var reg 1 B reset $end
$var reg 4 C d[3:0] $end
$var reg 4 D q[3:0] $end
$upscope $end
$scope module var_alarm $end
$var reg 1 E clk $end
$var reg 1 F reset $end
$var reg 1 G d $end
$var reg 1 H q $end
$upscope $end
$scope module gen_sub(1) $end
$upscope $end
$scope module gen_sub(2) $end
$upscope $end
$scope module gen_sub(3) $end
$upscope $end
$scope module gen_or(1) $end
$upscope $end
$scope module gen_or(2) $end
$upscope $end
$scope module gen_or(3) $end
$upscope $end
$upscope $end
$upscope $end
$enddefinitions $end
#0
1!
1"
b111 #
b1111 $
0%
0&
1'
1(
b111 )
0*
b111 +
b110 ,
b001 -
b111 .
0/
10
11
b110 2
b111 3
14
15
06
07
18
19
b1111 :
0;
b1111 <
b1110 =
b0001 >
b1111 ?
0@
1A
1B
b1110 C
b1111 D
1E
1F
0G
0H
#5000
0!
0'
00
04
08
0A
0E
#10000
1!
1'
10
14
18
1A
1E
#15000
0!
0'
00
04
08
0A
0E
#20000
1!
1'
10
14
18
1A
1E
#24000
0"
0(
01
05
09
0B
0F
#25000
0!
0'
00
04
08
0A
0E
#30000
1!
b110 #
b1110 $
1'
b110 )
b110 +
b101 ,
b011 -
b110 .
10
b101 2
b110 3
14
18
b1110 :
b1110 <
b1101 =
b0011 >
b1110 ?
1A
b1101 C
b1110 D
1E
#35000
0!
0'
00
04
08
0A
0E
#40000
1!
b101 #
b1101 $
1'
b101 )
b101 +
b100 ,
b001 -
b111 .
10
b100 2
b101 3
14
18
b1101 :
b1101 <
b1100 =
b0001 >
b1111 ?
1A
b1100 C
b1101 D
1E
#45000
0!
0'
00
04
08
0A
0E
#50000
1!
b100 #
b1100 $
1'
b100 )
b100 +
b011 ,
b111 -
b100 .
10
b011 2
b100 3
14
18
b1100 :
b1100 <
b1011 =
b0111 >
b1100 ?
1A
b1011 C
b1100 D
1E
#55000
0!
0'
00
04
08
0A
0E
#60000
1!
b011 #
b1011 $
1'
b011 )
b011 +
b010 ,
b001 -
b111 .
0/
10
b010 2
b011 3
14
06
18
b1011 :
b1011 <
b1010 =
b0001 >
b1111 ?
1A
b1010 C
b1011 D
1E
#65000
0!
0'
00
04
08
0A
0E
#70000
1!
b010 #
b1010 $
1'
b010 )
b010 +
b001 ,
b011 -
b110 .
10
b001 2
b010 3
14
18
b1010 :
b1010 <
b1001 =
b0011 >
b1110 ?
1A
b1001 C
b1010 D
1E
#75000
0!
0'
00
04
08
0A
0E
#80000
1!
b001 #
b1001 $
1'
b001 )
b001 +
b000 ,
b001 -
b111 .
0/
10
b000 2
b001 3
14
06
18
b1001 :
b1001 <
b1000 =
b0001 >
b1111 ?
1A
b1000 C
b1001 D
1E
#85000
0!
0'
00
04
08
0A
0E
#90000
1!
b000 #
b1000 $
1'
b000 )
b000 +
b111 ,
b111 -
b000 .
1/
10
b111 2
b000 3
14
16
18
b1000 :
b1000 <
b0111 =
b1111 >
b1000 ?
1A
b0111 C
b1000 D
1E
#95000
0!
0'
00
04
08
0A
0E
#100000
1!
b111 #
b0111 $
1%
1'
b111 )
1*
b111 +
b110 ,
b001 -
b111 .
0/
10
b110 2
b111 3
14
06
17
18
b0111 :
b0111 <
b0110 =
b0001 >
b1111 ?
0@
1A
b0110 C
b0111 D
1E
0G
#105000
0!
0'
00
04
08
0A
0E
#110000
1!
b110 #
b0110 $
0%
1'
b110 )
0*
b110 +
b101 ,
b011 -
b110 .
10
b101 2
b110 3
14
07
18
b0110 :
b0110 <
b0101 =
b0011 >
b1110 ?
1A
b0101 C
b0110 D
1E
#115000
0!
0'
00
04
08
0A
0E
#120000
1!
b101 #
b0101 $
1'
b101 )
b101 +
b100 ,
b001 -
b111 .
10
b100 2
b101 3
14
18
b0101 :
b0101 <
b0100 =
b0001 >
b1111 ?
1A
b0100 C
b0101 D
1E
#125000
0!
0'
00
04
08
0A
0E
#130000
1!
b100 #
b0100 $
1'
b100 )
b100 +
b011 ,
b111 -
b100 .
10
b011 2
b100 3
14
18
b0100 :
b0100 <
b0011 =
b0111 >
b1100 ?
1A
b0011 C
b0100 D
1E
#135000
0!
0'
00
04
08
0A
0E
#140000
1!
b011 #
b0011 $
1'
b011 )
b011 +
b010 ,
b001 -
b111 .
0/
10
b010 2
b011 3
14
06
18
b0011 :
b0011 <
b0010 =
b0001 >
b1111 ?
0@
1A
b0010 C
b0011 D
1E
0G
#145000
0!
0'
00
04
08
0A
0E
#150000
1!
b010 #
b0010 $
1'
b010 )
b010 +
b001 ,
b011 -
b110 .
10
b001 2
b010 3
14
18
b0010 :
b0010 <
b0001 =
b0011 >
b1110 ?
1A
b0001 C
b0010 D
1E
#155000
0!
0'
00
04
08
0A
0E
#160000
1!
b001 #
b0001 $
1'
b001 )
b001 +
b000 ,
b001 -
b111 .
0/
10
b000 2
b001 3
14
06
18
b0001 :
b0001 <
b0000 =
b0001 >
b1111 ?
0@
1A
b0000 C
b0001 D
1E
0G
#165000
0!
0'
00
04
08
0A
0E
#170000
1!
b000 #
b0000 $
1'
b000 )
b000 +
b111 ,
b111 -
b000 .
1/
10
b111 2
b000 3
14
16
18
b0000 :
b0000 <
b1111 =
b1111 >
b0000 ?
1@
1A
b1111 C
b0000 D
1E
1G
#175000
0!
0'
00
04
08
0A
0E
#180000
1!
b111 #
b1111 $
1%
1&
1'
b111 )
1*
b111 +
b110 ,
b001 -
b111 .
0/
10
b110 2
b111 3
14
06
17
18
b1111 :
1;
b1111 <
b1110 =
b0001 >
b1111 ?
0@
1A
b1110 C
b1111 D
1E
0G
1H
#185000
0!
0'
00
04
08
0A
0E
#190000
1!
b110 #
b1110 $
0%
0&
1'
b110 )
0*
b110 +
b101 ,
b011 -
b110 .
10
b101 2
b110 3
14
07
18
b1110 :
0;
b1110 <
b1101 =
b0011 >
b1110 ?
1A
b1101 C
b1110 D
1E
0H
#195000
0!
0'
00
04
08
0A
0E
#200000
1!
b101 #
b1101 $
1'
b101 )
b101 +
b100 ,
b001 -
b111 .
10
b100 2
b101 3
14
18
b1101 :
b1101 <
b1100 =
b0001 >
b1111 ?
1A
b1100 C
b1101 D
1E
#205000
0!
0'
00
04
08
0A
0E
#210000
1!
b100 #
b1100 $
1'
b100 )
b100 +
b011 ,
b111 -
b100 .
10
b011 2
b100 3
14
18
b1100 :
b1100 <
b1011 =
b0111 >
b1100 ?
1A
b1011 C
b1100 D
1E
#215000
0!
0'
00
04
08
0A
0E
#220000
1!
b011 #
b1011 $
1'
b011 )
b011 +
b010 ,
b001 -
b111 .
0/
10
b010 2
b011 3
14
06
18
b1011 :
b1011 <
b1010 =
b0001 >
b1111 ?
1A
b1010 C
b1011 D
1E
#225000
0!
0'
00
04
08
0A
0E
#230000
1!
b010 #
b1010 $
1'
b010 )
b010 +
b001 ,
b011 -
b110 .
10
b001 2
b010 3
14
18
b1010 :
b1010 <
b1001 =
b0011 >
b1110 ?
1A
b1001 C
b1010 D
1E
#235000
0!
0'
00
04
08
0A
0E
#240000
1!
b001 #
b1001 $
1'
b001 )
b001 +
b000 ,
b001 -
b111 .
0/
10
b000 2
b001 3
14
06
18
b1001 :
b1001 <
b1000 =
b0001 >
b1111 ?
1A
b1000 C
b1001 D
1E
#245000
0!
0'
00
04
08
0A
0E
#250000
1!
b000 #
b1000 $
1'
b000 )
b000 +
b111 ,
b111 -
b000 .
1/
10
b111 2
b000 3
14
16
18
b1000 :
b1000 <
b0111 =
b1111 >
b1000 ?
1A
b0111 C
b1000 D
1E
#255000
0!
0'
00
04
08
0A
0E
#260000
1!
b111 #
b0111 $
1%
1'
b111 )
1*
b111 +
b110 ,
b001 -
b111 .
0/
10
b110 2
b111 3
14
06
17
18
b0111 :
b0111 <
b0110 =
b0001 >
b1111 ?
0@
1A
b0110 C
b0111 D
1E
0G
#265000
0!
0'
00
04
08
0A
0E
#270000
1!
b110 #
b0110 $
0%
1'
b110 )
0*
b110 +
b101 ,
b011 -
b110 .
10
b101 2
b110 3
14
07
18
b0110 :
b0110 <
b0101 =
b0011 >
b1110 ?
1A
b0101 C
b0110 D
1E
#275000
0!
0'
00
04
08
0A
0E
#280000
1!
b101 #
b0101 $
1'
b101 )
b101 +
b100 ,
b001 -
b111 .
10
b100 2
b101 3
14
18
b0101 :
b0101 <
b0100 =
b0001 >
b1111 ?
1A
b0100 C
b0101 D
1E
#285000
0!
0'
00
04
08
0A
0E
#290000
1!
b100 #
b0100 $
1'
b100 )
b100 +
b011 ,
b111 -
b100 .
10
b011 2
b100 3
14
18
b0100 :
b0100 <
b0011 =
b0111 >
b1100 ?
1A
b0011 C
b0100 D
1E
#295000
0!
0'
00
04
08
0A
0E
#300000
1!
b011 #
b0011 $
1'
b011 )
b011 +
b010 ,
b001 -
b111 .
0/
10
b010 2
b011 3
14
06
18
b0011 :
b0011 <
b0010 =
b0001 >
b1111 ?
0@
1A
b0010 C
b0011 D
1E
0G
#305000
0!
0'
00
04
08
0A
0E
#310000
1!
b010 #
b0010 $
1'
b010 )
b010 +
b001 ,
b011 -
b110 .
10
b001 2
b010 3
14
18
b0010 :
b0010 <
b0001 =
b0011 >
b1110 ?
1A
b0001 C
b0010 D
1E
#315000
0!
0'
00
04
08
0A
0E
#320000
1!
b001 #
b0001 $
1'
b001 )
b001 +
b000 ,
b001 -
b111 .
0/
10
b000 2
b001 3
14
06
18
b0001 :
b0001 <
b0000 =
b0001 >
b1111 ?
0@
1A
b0000 C
b0001 D
1E
0G
#325000
0!
0'
00
04
08
0A
0E
#330000
1!
b000 #
b0000 $
1'
b000 )
b000 +
b111 ,
b111 -
b000 .
1/
10
b111 2
b000 3
14
16
18
b0000 :
b0000 <
b1111 =
b1111 >
b0000 ?
1@
1A
b1111 C
b0000 D
1E
1G
#335000
0!
0'
00
04
08
0A
0E
#340000
1!
b111 #
b1111 $
1%
1&
1'
b111 )
1*
b111 +
b110 ,
b001 -
b111 .
0/
10
b110 2
b111 3
14
06
17
18
b1111 :
1;
b1111 <
b1110 =
b0001 >
b1111 ?
0@
1A
b1110 C
b1111 D
1E
0G
1H
