CarryRippleAdder/src/fa_ea_struct.vhd
library IEEE;
use IEEE.STD_LOGIC_1164.all;

entity fa is
  port(a, b, cin: in  std_ulogic;
       cout, s:   out std_ulogic);
end;

architecture struct of fa is
begin
    cout <= (a and b) or (a and cin) or (b and cin);
    s <= a xor b xor cin;
end;

CarryRippleAdder/src/cra_ea_struct.vhd
library IEEE;
use IEEE.STD_LOGIC_1164.all;
entity cra is
  port(a, b: in  std_ulogic_vector(3 downto 0);
       cin:  in  std_ulogic;
       cout: out std_ulogic;
       sum:  out std_ulogic_vector(3 downto 0));
end;

architecture struct of cra is
    component fa --Wiederholung der Komponent damit wir sie nutzen können
        port(a, b, cin: in std_ulogic;
            cout, s: out std_ulogic);
    end component;
    signal c1, c2, c3: std_ulogic; -- mit den Signalen verbinden wir Cout und Cin der FAs
begin   
    -- <name> : <komponente> port map(<signale und ports>);
    fa0: fa port map(a(0), b(0), cin, c1, sum(0));
    fa1: fa port map(a(1), b(1), c1, c2, sum(1));
    fa2: fa port map(a(2), b(2), c2, c3, sum(2));
    fa3: fa port map(a(3), b(3), c3, cout, sum(3));
end;



library IEEE;
use IEEE.STD_LOGIC_1164.all;
entity cra_gen is
  generic(width: integer);
  port(a, b: in  std_ulogic_vector(width-1 downto 0);
       cin:  in  std_ulogic;
       cout: out std_ulogic;
       sum:  out std_ulogic_vector(width-1 downto 0));
end;    

architecture struct of cra_gen is
  component fa --Wiederholung der Komponent damit wir sie nutzen können
    port(a, b, cin: in  std_ulogic;
         cout, s:   out std_ulogic);
  end component;
--    signal c1, c2, c3: STD_ULOGIC; -- mit den Signalen verbinden wir Cout und Cin der FAs
  signal c: std_ulogic_vector(width-1 downto 0);
begin
  
  fa0: fa port map(a(0), b(0), cin, c(0), sum(0));
  
  FA_1: for I in 1 to width-1 generate
    faN: fa port map(a(I), b(I), c(I-1), c(I), sum(I));
  end generate;
  
  cout <= c(width-1);
end;

CarryRippleAdder/tb/testbench.vhd
library IEEE;
use IEEE.STD_LOGIC_1164.all;
use IEEE.NUMERIC_STD.all;

entity testbench is
end;


architecture bhv of testbench is
  component cra
    port(a, b: in  std_ulogic_vector(3 downto 0);
         cin:  in  std_ulogic;
         cout: out std_ulogic;
         sum:  out std_ulogic_vector(3 downto 0));
  end component;
  component cra_gen
    generic(width: integer);
        port(a, b: in  std_ulogic_vector(width-1 downto 0);
            cin:   in  std_ulogic;
            cout:  out std_ulogic;
            sum:   out std_ulogic_vector(width-1 downto 0));
  end component;
  
  constant width : integer := 4;
  signal a, b: std_ulogic_vector(3 downto 0);
  signal y:    std_ulogic_vector(4 downto 0);
  
begin
    cra_comp: cra port map(a, b, '0', y(4), y(3 downto 0));
--    cra_comp: cra_gen generic map(4) port map(a, b, '0', y(4), y(3 downto 0));

    process begin
        report "-- TRIAL CHECKS --";
        a <= std_ulogic_vector(to_unsigned(5, a'length));
        b <= std_ulogic_vector(to_unsigned(2, b'length));
        wait for 40 ns;
        report "5 + 2 = " & integer'image(to_integer(unsigned(y)));

        a <= std_ulogic_vector(to_unsigned(1, a'length));
        b <= std_ulogic_vector(to_unsigned(11, b'length));
        wait for 40 ns;
        report "1 + 11 = " & integer'image(to_integer(unsigned(y)));
        
        a <= STD_ULOGIC_VECTOR(to_unsigned(7, a'length));
        b <= STD_ULOGIC_VECTOR(to_unsigned(7, b'length));
        wait for 40 ns;
        report "7 + 7 = " & integer'image(to_integer(unsigned(y)));

        report "-- ERROR CHECKS --";
        for aa in 0 to 15 loop
            for bb in 0 to 15 loop
                a <= std_ulogic_vector(to_unsigned(aa, a'length));
                b <= std_ulogic_vector(to_unsigned(bb, b'length));
                wait for 5 ns;
                if(aa+bb /= to_integer(unsigned(y))) then
                    report integer'image(aa) & " + " & integer'image(bb) & " = " & integer'image(to_integer(unsigned(y))) severity error;
                    wait;
                end if;
            end loop;
        end loop;
        report "all done";
        wait;
    end process;
end;

CarryRippleAdder/sim/result.vcd
$date
  Sun Apr 12 13:26:04 2026
$end
$version
  GHDL v0
$end
$timescale
  1 fs
$end
$scope module standard $end
$upscope $end
$scope module textio $end
$upscope $end
$scope module std_logic_1164 $end
$upscope $end
$scope module numeric_std $end
$upscope $end
$scope module testbench $end
$var reg 4 ! a[3:0] $end
$var reg 4 " b[3:0] $end
$var reg 5 # y[4:0] $end
$scope module cra_comp $end
$var reg 4 $ a[3:0] $end
$var reg 4 % b[3:0] $end
$var reg 1 & cin $end
$var reg 1 ' cout $end
$var reg 4 ( sum[3:0] $end
$var reg 1 ) c1 $end
$var reg 1 * c2 $end
$var reg 1 + c3 $end
$scope module fa0 $end
$var reg 1 , a $end
$var reg 1 - b $end
$var reg 1 . cin $end
$var reg 1 / cout $end
$var reg 1 0 s $end
$upscope $end
$scope module fa1 $end
$var reg 1 1 a $end
$var reg 1 2 b $end
$var reg 1 3 cin $end
$var reg 1 4 cout $end
$var reg 1 5 s $end
$upscope $end
$scope module fa2 $end
$var reg 1 6 a $end
$var reg 1 7 b $end
$var reg 1 8 cin $end
$var reg 1 9 cout $end
$var reg 1 : s $end
$upscope $end
$scope module fa3 $end
$var reg 1 ; a $end
$var reg 1 < b $end
$var reg 1 = cin $end
$var reg 1 > cout $end
$var reg 1 ? s $end
$upscope $end
$upscope $end
$upscope $end
$enddefinitions $end
#0
b0101 !
b0010 "
b00111 #
b0101 $
b0010 %
0&
0'
b0111 (
0)
0*
0+
1,
0-
0.
0/
10
01
12
03
04
15
16
07
08
09
1:
0;
0<
0=
0>
0?
#40000000
b0001 !
b1011 "
b01100 #
b0001 $
b1011 %
b1100 (
1)
1*
1-
1/
00
13
14
05
06
18
1:
1<
1?
#80000000
b0111 !
b0111 "
b01110 #
b0111 $
b0111 %
b1110 (
1+
11
15
16
17
19
0<
1=
1?
#120000000
b0000 !
b0000 "
b00000 #
b0000 $
b0000 %
b0000 (
0)
0*
0+
0,
0-
0/
01
02
03
04
05
06
07
08
09
0:
0=
0?
#125000000
b0001 "
b00001 #
b0001 %
b0001 (
1-
10
#130000000
b0010 "
b00010 #
b0010 %
b0010 (
0-
00
12
15
#135000000
b0011 "
b00011 #
b0011 %
b0011 (
1-
10
#140000000
b0100 "
b00100 #
b0100 %
b0100 (
0-
00
02
05
17
1:
#145000000
b0101 "
b00101 #
b0101 %
b0101 (
1-
10
#150000000
b0110 "
b00110 #
b0110 %
b0110 (
0-
00
12
15
#155000000
b0111 "
b00111 #
b0111 %
b0111 (
1-
10
#160000000
b1000 "
b01000 #
b1000 %
b1000 (
0-
00
02
05
07
0:
1<
1?
#165000000
b1001 "
b01001 #
b1001 %
b1001 (
1-
10
#170000000
b1010 "
b01010 #
b1010 %
b1010 (
0-
00
12
15
#175000000
b1011 "
b01011 #
b1011 %
b1011 (
1-
10
#180000000
b1100 "
b01100 #
b1100 %
b1100 (
0-
00
02
05
17
1:
#185000000
b1101 "
b01101 #
b1101 %
b1101 (
1-
10
#190000000
b1110 "
b01110 #
b1110 %
b1110 (
0-
00
12
15
#195000000
b1111 "
b01111 #
b1111 %
b1111 (
1-
10
#200000000
b0001 !
b0000 "
b00001 #
b0001 $
b0000 %
b0001 (
1,
0-
02
05
07
0:
0<
0?
#205000000
b0001 "
b00010 #
b0001 %
b0010 (
1)
1-
1/
00
13
15
#210000000
b0010 "
b00011 #
b0010 %
b0011 (
0)
0*
0-
0/
10
12
03
04
15
08
0:
#215000000
b0011 "
b00100 #
b0011 %
b0100 (
1)
1*
1-
1/
00
13
14
05
18
1:
#220000000
b0100 "
b00101 #
b0100 %
b0101 (
0)
0*
0+
0-
0/
10
02
03
04
05
17
08
09
1:
0=
0?
#225000000
b0101 "
b00110 #
b0101 %
b0110 (
1)
1-
1/
00
13
15
#230000000
b0110 "
b00111 #
b0110 %
b0111 (
0)
0*
0+
0-
0/
10
12
03
04
15
08
09
1:
0=
0?
#235000000
b0111 "
b01000 #
b0111 %
b1000 (
1)
1*
1+
1-
1/
00
13
14
05
18
19
0:
1=
1?
#240000000
b1000 "
b01001 #
b1000 %
0'
b1001 (
0)
0*
0+
0-
0/
10
02
03
04
05
07
08
09
0:
1<
0=
0>
1?
#245000000
b1001 "
b01010 #
b1001 %
b1010 (
1)
1-
1/
00
13
15
#250000000
b1010 "
b01011 #
b1010 %
b1011 (
0)
0*
0-
0/
10
12
03
04
15
08
0:
#255000000
b1011 "
b01100 #
b1011 %
b1100 (
1)
1*
1-
1/
00
13
14
05
18
1:
#260000000
b1100 "
b01101 #
b1100 %
0'
b1101 (
0)
0*
0+
0-
0/
10
02
03
04
05
17
08
09
1:
0=
0>
1?
#265000000
b1101 "
b01110 #
b1101 %
b1110 (
1)
1-
1/
00
13
15
#270000000
b1110 "
b01111 #
b1110 %
0'
b1111 (
0)
0*
0+
0-
0/
10
12
03
04
15
08
09
1:
0=
0>
1?
#275000000
b1111 "
b10000 #
b1111 %
1'
b0000 (
1)
1*
1+
1-
1/
00
13
14
05
18
19
0:
1=
1>
0?
#280000000
b0010 !
b0000 "
b00010 #
b0010 $
b0000 %
0'
b0010 (
0)
0*
0+
0,
0-
0/
11
02
03
04
15
07
08
09
0:
0<
0=
0>
0?
#285000000
b0001 "
b00011 #
b0001 %
b0011 (
1-
10
#290000000
b0010 "
b00100 #
b0010 %
b0100 (
1*
0-
00
12
14
05
18
1:
#295000000
b0011 "
b00101 #
b0011 %
b0101 (
1-
10
#300000000
b0100 "
b00110 #
b0100 %
b0110 (
0*
0+
0-
00
02
04
15
17
08
09
1:
0=
0?
#305000000
b0101 "
b00111 #
b0101 %
b0111 (
1-
10
#310000000
b0110 "
b01000 #
b0110 %
b1000 (
1*
1+
0-
00
12
14
05
18
19
0:
1=
1?
#315000000
b0111 "
b01001 #
b0111 %
b1001 (
1-
10
#320000000
b1000 "
b01010 #
b1000 %
0'
b1010 (
0*
0+
0-
00
02
04
15
07
08
09
0:
1<
0=
0>
1?
#325000000
b1001 "
b01011 #
b1001 %
b1011 (
1-
10
#330000000
b1010 "
b01100 #
b1010 %
b1100 (
1*
0-
00
12
14
05
18
1:
#335000000
b1011 "
b01101 #
b1011 %
b1101 (
1-
10
#340000000
b1100 "
b01110 #
b1100 %
0'
b1110 (
0*
0+
0-
00
02
04
15
17
08
09
1:
0=
0>
1?
#345000000
b1101 "
b01111 #
b1101 %
b1111 (
1-
10
#350000000
b1110 "
b10000 #
b1110 %
1'
b0000 (
1*
1+
0-
00
12
14
05
18
19
0:
1=
1>
0?
#355000000
b1111 "
b10001 #
b1111 %
b0001 (
1-
10
#360000000
b0011 !
b0000 "
b00011 #
b0011 $
b0000 %
0'
b0011 (
0*
0+
1,
0-
02
04
15
07
08
09
0:
0<
0=
0>
0?
#365000000
b0001 "
b00100 #
b0001 %
b0100 (
1)
1*
1-
1/
00
13
14
05
18
1:
#370000000
b0010 "
b00101 #
b0010 %
b0101 (
0)
0-
0/
10
12
03
05
#375000000
b0011 "
b00110 #
b0011 %
b0110 (
1)
1-
1/
00
13
15
#380000000
b0100 "
b00111 #
b0100 %
b0111 (
0)
0*
0+
0-
0/
10
02
03
04
15
17
08
09
1:
0=
0?
#385000000
b0101 "
b01000 #
b0101 %
b1000 (
1)
1*
1+
1-
1/
00
13
14
05
18
19
0:
1=
1?
#390000000
b0110 "
b01001 #
b0110 %
b1001 (
0)
0-
0/
10
12
03
05
#395000000
b0111 "
b01010 #
b0111 %
b1010 (
1)
1-
1/
00
13
15
#400000000
b1000 "
b01011 #
b1000 %
0'
b1011 (
0)
0*
0+
0-
0/
10
02
03
04
15
07
08
09
0:
1<
0=
0>
1?
#405000000
b1001 "
b01100 #
b1001 %
b1100 (
1)
1*
1-
1/
00
13
14
05
18
1:
#410000000
b1010 "
b01101 #
b1010 %
b1101 (
0)
0-
0/
10
12
03
05
#415000000
b1011 "
b01110 #
b1011 %
b1110 (
1)
1-
1/
00
13
15
#420000000
b1100 "
b01111 #
b1100 %
0'
b1111 (
0)
0*
0+
0-
0/
10
02
03
04
15
17
08
09
1:
0=
0>
1?
#425000000
b1101 "
b10000 #
b1101 %
1'
b0000 (
1)
1*
1+
1-
1/
00
13
14
05
18
19
0:
1=
1>
0?
#430000000
b1110 "
b10001 #
b1110 %
b0001 (
0)
0-
0/
10
12
03
05
#435000000
b1111 "
b10010 #
b1111 %
b0010 (
1)
1-
1/
00
13
15
#440000000
b0100 !
b0000 "
b00100 #
b0100 $
b0000 %
0'
b0100 (
0)
0*
0+
0,
0-
0/
01
02
03
04
05
16
07
08
09
1:
0<
0=
0>
0?
#445000000
b0001 "
b00101 #
b0001 %
b0101 (
1-
10
#450000000
b0010 "
b00110 #
b0010 %
b0110 (
0-
00
12
15
#455000000
b0011 "
b00111 #
b0011 %
b0111 (
1-
10
#460000000
b0100 "
b01000 #
b0100 %
b1000 (
1+
0-
00
02
05
17
19
0:
1=
1?
#465000000
b0101 "
b01001 #
b0101 %
b1001 (
1-
10
#470000000
b0110 "
b01010 #
b0110 %
b1010 (
0-
00
12
15
#475000000
b0111 "
b01011 #
b0111 %
b1011 (
1-
10
#480000000
b1000 "
b01100 #
b1000 %
0'
b1100 (
0+
0-
00
02
05
07
09
1:
1<
0=
0>
1?
#485000000
b1001 "
b01101 #
b1001 %
b1101 (
1-
10
#490000000
b1010 "
b01110 #
b1010 %
b1110 (
0-
00
12
15
#495000000
b1011 "
b01111 #
b1011 %
b1111 (
1-
10
#500000000
b1100 "
b10000 #
b1100 %
1'
b0000 (
1+
0-
00
02
05
17
19
0:
1=
1>
0?
#505000000
b1101 "
b10001 #
b1101 %
b0001 (
1-
10
#510000000
b1110 "
b10010 #
b1110 %
b0010 (
0-
00
12
15
#515000000
b1111 "
b10011 #
b1111 %
b0011 (
1-
10
#520000000
b0101 !
b0000 "
b00101 #
b0101 $
b0000 %
0'
b0101 (
0+
1,
0-
02
05
07
09
1:
0<
0=
0>
0?
#525000000
b0001 "
b00110 #
b0001 %
b0110 (
1)
1-
1/
00
13
15
#530000000
b0010 "
b00111 #
b0010 %
b0111 (
0)
0*
0+
0-
0/
10
12
03
04
15
08
09
1:
0=
0?
#535000000
b0011 "
b01000 #
b0011 %
b1000 (
1)
1*
1+
1-
1/
00
13
14
05
18
19
0:
1=
1?
#540000000
b0100 "
b01001 #
b0100 %
b1001 (
0)
0*
0-
0/
10
02
03
04
05
17
08
0:
#545000000
b0101 "
b01010 #
b0101 %
b1010 (
1)
1-
1/
00
13
15
#550000000
b0110 "
b01011 #
b0110 %
b1011 (
0)
0*
0-
0/
10
12
03
04
15
08
0:
#555000000
b0111 "
b01100 #
b0111 %
b1100 (
1)
1*
1-
1/
00
13
14
05
18
1:
#560000000
b1000 "
b01101 #
b1000 %
0'
b1101 (
0)
0*
0+
0-
0/
10
02
03
04
05
07
08
09
1:
1<
0=
0>
1?
#565000000
b1001 "
b01110 #
b1001 %
b1110 (
1)
1-
1/
00
13
15
#570000000
b1010 "
b01111 #
b1010 %
0'
b1111 (
0)
0*
0+
0-
0/
10
12
03
04
15
08
09
1:
0=
0>
1?
#575000000
b1011 "
b10000 #
b1011 %
1'
b0000 (
1)
1*
1+
1-
1/
00
13
14
05
18
19
0:
1=
1>
0?
#580000000
b1100 "
b10001 #
b1100 %
b0001 (
0)
0*
0-
0/
10
02
03
04
05
17
08
0:
#585000000
b1101 "
b10010 #
b1101 %
b0010 (
1)
1-
1/
00
13
15
#590000000
b1110 "
b10011 #
b1110 %
b0011 (
0)
0*
0-
0/
10
12
03
04
15
08
0:
#595000000
b1111 "
b10100 #
b1111 %
b0100 (
1)
1*
1-
1/
00
13
14
05
18
1:
#600000000
b0110 !
b0000 "
b00110 #
b0110 $
b0000 %
0'
b0110 (
0)
0*
0+
0,
0-
0/
11
02
03
04
15
07
08
09
1:
0<
0=
0>
0?
#605000000
b0001 "
b00111 #
b0001 %
b0111 (
1-
10
#610000000
b0010 "
b01000 #
b0010 %
b1000 (
1*
1+
0-
00
12
14
05
18
19
0:
1=
1?
#615000000
b0011 "
b01001 #
b0011 %
b1001 (
1-
10
#620000000
b0100 "
b01010 #
b0100 %
b1010 (
0*
0-
00
02
04
15
17
08
0:
#625000000
b0101 "
b01011 #
b0101 %
b1011 (
1-
10
#630000000
b0110 "
b01100 #
b0110 %
b1100 (
1*
0-
00
12
14
05
18
1:
#635000000
b0111 "
b01101 #
b0111 %
b1101 (
1-
10
#640000000
b1000 "
b01110 #
b1000 %
0'
b1110 (
0*
0+
0-
00
02
04
15
07
08
09
1:
1<
0=
0>
1?
#645000000
b1001 "
b01111 #
b1001 %
b1111 (
1-
10
#650000000
b1010 "
b10000 #
b1010 %
1'
b0000 (
1*
1+
0-
00
12
14
05
18
19
0:
1=
1>
0?
#655000000
b1011 "
b10001 #
b1011 %
b0001 (
1-
10
#660000000
b1100 "
b10010 #
b1100 %
b0010 (
0*
0-
00
02
04
15
17
08
0:
#665000000
b1101 "
b10011 #
b1101 %
b0011 (
1-
10
#670000000
b1110 "
b10100 #
b1110 %
b0100 (
1*
0-
00
12
14
05
18
1:
#675000000
b1111 "
b10101 #
b1111 %
b0101 (
1-
10
#680000000
b0111 !
b0000 "
b00111 #
b0111 $
b0000 %
0'
b0111 (
0*
0+
1,
0-
02
04
15
07
08
09
1:
0<
0=
0>
0?
#685000000
b0001 "
b01000 #
b0001 %
b1000 (
1)
1*
1+
1-
1/
00
13
14
05
18
19
0:
1=
1?
#690000000
b0010 "
b01001 #
b0010 %
b1001 (
0)
0-
0/
10
12
03
05
#695000000
b0011 "
b01010 #
b0011 %
b1010 (
1)
1-
1/
00
13
15
#700000000
b0100 "
b01011 #
b0100 %
b1011 (
0)
0*
0-
0/
10
02
03
04
15
17
08
0:
#705000000
b0101 "
b01100 #
b0101 %
b1100 (
1)
1*
1-
1/
00
13
14
05
18
1:
#710000000
b0110 "
b01101 #
b0110 %
b1101 (
0)
0-
0/
10
12
03
05
#715000000
b0111 "
b01110 #
b0111 %
b1110 (
1)
1-
1/
00
13
15
#720000000
b1000 "
b01111 #
b1000 %
0'
b1111 (
0)
0*
0+
0-
0/
10
02
03
04
15
07
08
09
1:
1<
0=
0>
1?
#725000000
b1001 "
b10000 #
b1001 %
1'
b0000 (
1)
1*
1+
1-
1/
00
13
14
05
18
19
0:
1=
1>
0?
#730000000
b1010 "
b10001 #
b1010 %
b0001 (
0)
0-
0/
10
12
03
05
#735000000
b1011 "
b10010 #
b1011 %
b0010 (
1)
1-
1/
00
13
15
#740000000
b1100 "
b10011 #
b1100 %
b0011 (
0)
0*
0-
0/
10
02
03
04
15
17
08
0:
#745000000
b1101 "
b10100 #
b1101 %
b0100 (
1)
1*
1-
1/
00
13
14
05
18
1:
#750000000
b1110 "
b10101 #
b1110 %
b0101 (
0)
0-
0/
10
12
03
05
#755000000
b1111 "
b10110 #
b1111 %
b0110 (
1)
1-
1/
00
13
15
#760000000
b1000 !
b0000 "
b01000 #
b1000 $
b0000 %
0'
b1000 (
0)
0*
0+
0,
0-
0/
01
02
03
04
05
06
07
08
09
0:
1;
0<
0=
0>
1?
#765000000
b0001 "
b01001 #
b0001 %
b1001 (
1-
10
#770000000
b0010 "
b01010 #
b0010 %
b1010 (
0-
00
12
15
#775000000
b0011 "
b01011 #
b0011 %
b1011 (
1-
10
#780000000
b0100 "
b01100 #
b0100 %
b1100 (
0-
00
02
05
17
1:
#785000000
b0101 "
b01101 #
b0101 %
b1101 (
1-
10
#790000000
b0110 "
b01110 #
b0110 %
b1110 (
0-
00
12
15
#795000000
b0111 "
b01111 #
b0111 %
b1111 (
1-
10
#800000000
b1000 "
b10000 #
b1000 %
1'
b0000 (
0-
00
02
05
07
0:
1<
1>
0?
#805000000
b1001 "
b10001 #
b1001 %
b0001 (
1-
10
#810000000
b1010 "
b10010 #
b1010 %
b0010 (
0-
00
12
15
#815000000
b1011 "
b10011 #
b1011 %
b0011 (
1-
10
#820000000
b1100 "
b10100 #
b1100 %
b0100 (
0-
00
02
05
17
1:
#825000000
b1101 "
b10101 #
b1101 %
b0101 (
1-
10
#830000000
b1110 "
b10110 #
b1110 %
b0110 (
0-
00
12
15
#835000000
b1111 "
b10111 #
b1111 %
b0111 (
1-
10
#840000000
b1001 !
b0000 "
b01001 #
b1001 $
b0000 %
0'
b1001 (
1,
0-
02
05
07
0:
0<
0>
1?
#845000000
b0001 "
b01010 #
b0001 %
b1010 (
1)
1-
1/
00
13
15
#850000000
b0010 "
b01011 #
b0010 %
b1011 (
0)
0*
0-
0/
10
12
03
04
15
08
0:
#855000000
b0011 "
b01100 #
b0011 %
b1100 (
1)
1*
1-
1/
00
13
14
05
18
1:
#860000000
b0100 "
b01101 #
b0100 %
0'
b1101 (
0)
0*
0+
0-
0/
10
02
03
04
05
17
08
09
1:
0=
0>
1?
#865000000
b0101 "
b01110 #
b0101 %
b1110 (
1)
1-
1/
00
13
15
#870000000
b0110 "
b01111 #
b0110 %
0'
b1111 (
0)
0*
0+
0-
0/
10
12
03
04
15
08
09
1:
0=
0>
1?
#875000000
b0111 "
b10000 #
b0111 %
1'
b0000 (
1)
1*
1+
1-
1/
00
13
14
05
18
19
0:
1=
1>
0?
#880000000
b1000 "
b10001 #
b1000 %
b0001 (
0)
0*
0+
0-
0/
10
02
03
04
05
07
08
09
0:
1<
0=
0?
#885000000
b1001 "
b10010 #
b1001 %
b0010 (
1)
1-
1/
00
13
15
#890000000
b1010 "
b10011 #
b1010 %
b0011 (
0)
0*
0-
0/
10
12
03
04
15
08
0:
#895000000
b1011 "
b10100 #
b1011 %
b0100 (
1)
1*
1-
1/
00
13
14
05
18
1:
#900000000
b1100 "
b10101 #
b1100 %
b0101 (
0)
0*
0+
0-
0/
10
02
03
04
05
17
08
09
1:
0=
0?
#905000000
b1101 "
b10110 #
b1101 %
b0110 (
1)
1-
1/
00
13
15
#910000000
b1110 "
b10111 #
b1110 %
b0111 (
0)
0*
0+
0-
0/
10
12
03
04
15
08
09
1:
0=
0?
#915000000
b1111 "
b11000 #
b1111 %
b1000 (
1)
1*
1+
1-
1/
00
13
14
05
18
19
0:
1=
1?
#920000000
b1010 !
b0000 "
b01010 #
b1010 $
b0000 %
0'
b1010 (
0)
0*
0+
0,
0-
0/
11
02
03
04
15
07
08
09
0:
0<
0=
0>
1?
#925000000
b0001 "
b01011 #
b0001 %
b1011 (
1-
10
#930000000
b0010 "
b01100 #
b0010 %
b1100 (
1*
0-
00
12
14
05
18
1:
#935000000
b0011 "
b01101 #
b0011 %
b1101 (
1-
10
#940000000
b0100 "
b01110 #
b0100 %
0'
b1110 (
0*
0+
0-
00
02
04
15
17
08
09
1:
0=
0>
1?
#945000000
b0101 "
b01111 #
b0101 %
b1111 (
1-
10
#950000000
b0110 "
b10000 #
b0110 %
1'
b0000 (
1*
1+
0-
00
12
14
05
18
19
0:
1=
1>
0?
#955000000
b0111 "
b10001 #
b0111 %
b0001 (
1-
10
#960000000
b1000 "
b10010 #
b1000 %
b0010 (
0*
0+
0-
00
02
04
15
07
08
09
0:
1<
0=
0?
#965000000
b1001 "
b10011 #
b1001 %
b0011 (
1-
10
#970000000
b1010 "
b10100 #
b1010 %
b0100 (
1*
0-
00
12
14
05
18
1:
#975000000
b1011 "
b10101 #
b1011 %
b0101 (
1-
10
#980000000
b1100 "
b10110 #
b1100 %
b0110 (
0*
0+
0-
00
02
04
15
17
08
09
1:
0=
0?
#985000000
b1101 "
b10111 #
b1101 %
b0111 (
1-
10
#990000000
b1110 "
b11000 #
b1110 %
b1000 (
1*
1+
0-
00
12
14
05
18
19
0:
1=
1?
#995000000
b1111 "
b11001 #
b1111 %
b1001 (
1-
10
#1000000000
b1011 !
b0000 "
b01011 #
b1011 $
b0000 %
0'
b1011 (
0*
0+
1,
0-
02
04
15
07
08
09
0:
0<
0=
0>
1?
#1005000000
b0001 "
b01100 #
b0001 %
b1100 (
1)
1*
1-
1/
00
13
14
05
18
1:
#1010000000
b0010 "
b01101 #
b0010 %
b1101 (
0)
0-
0/
10
12
03
05
#1015000000
b0011 "
b01110 #
b0011 %
b1110 (
1)
1-
1/
00
13
15
#1020000000
b0100 "
b01111 #
b0100 %
0'
b1111 (
0)
0*
0+
0-
0/
10
02
03
04
15
17
08
09
1:
0=
0>
1?
#1025000000
b0101 "
b10000 #
b0101 %
1'
b0000 (
1)
1*
1+
1-
1/
00
13
14
05
18
19
0:
1=
1>
0?
#1030000000
b0110 "
b10001 #
b0110 %
b0001 (
0)
0-
0/
10
12
03
05
#1035000000
b0111 "
b10010 #
b0111 %
b0010 (
1)
1-
1/
00
13
15
#1040000000
b1000 "
b10011 #
b1000 %
b0011 (
0)
0*
0+
0-
0/
10
02
03
04
15
07
08
09
0:
1<
0=
0?
#1045000000
b1001 "
b10100 #
b1001 %
b0100 (
1)
1*
1-
1/
00
13
14
05
18
1:
#1050000000
b1010 "
b10101 #
b1010 %
b0101 (
0)
0-
0/
10
12
03
05
#1055000000
b1011 "
b10110 #
b1011 %
b0110 (
1)
1-
1/
00
13
15
#1060000000
b1100 "
b10111 #
b1100 %
b0111 (
0)
0*
0+
0-
0/
10
02
03
04
15
17
08
09
1:
0=
0?
#1065000000
b1101 "
b11000 #
b1101 %
b1000 (
1)
1*
1+
1-
1/
00
13
14
05
18
19
0:
1=
1?
#1070000000
b1110 "
b11001 #
b1110 %
b1001 (
0)
0-
0/
10
12
03
05
#1075000000
b1111 "
b11010 #
b1111 %
b1010 (
1)
1-
1/
00
13
15
#1080000000
b1100 !
b0000 "
b01100 #
b1100 $
b0000 %
0'
b1100 (
0)
0*
0+
0,
0-
0/
01
02
03
04
05
16
07
08
09
1:
0<
0=
0>
1?
#1085000000
b0001 "
b01101 #
b0001 %
b1101 (
1-
10
#1090000000
b0010 "
b01110 #
b0010 %
b1110 (
0-
00
12
15
#1095000000
b0011 "
b01111 #
b0011 %
b1111 (
1-
10
#1100000000
b0100 "
b10000 #
b0100 %
1'
b0000 (
1+
0-
00
02
05
17
19
0:
1=
1>
0?
#1105000000
b0101 "
b10001 #
b0101 %
b0001 (
1-
10
#1110000000
b0110 "
b10010 #
b0110 %
b0010 (
0-
00
12
15
#1115000000
b0111 "
b10011 #
b0111 %
b0011 (
1-
10
#1120000000
b1000 "
b10100 #
b1000 %
b0100 (
0+
0-
00
02
05
07
09
1:
1<
0=
0?
#1125000000
b1001 "
b10101 #
b1001 %
b0101 (
1-
10
#1130000000
b1010 "
b10110 #
b1010 %
b0110 (
0-
00
12
15
#1135000000
b1011 "
b10111 #
b1011 %
b0111 (
1-
10
#1140000000
b1100 "
b11000 #
b1100 %
b1000 (
1+
0-
00
02
05
17
19
0:
1=
1?
#1145000000
b1101 "
b11001 #
b1101 %
b1001 (
1-
10
#1150000000
b1110 "
b11010 #
b1110 %
b1010 (
0-
00
12
15
#1155000000
b1111 "
b11011 #
b1111 %
b1011 (
1-
10
#1160000000
b1101 !
b0000 "
b01101 #
b1101 $
b0000 %
0'
b1101 (
0+
1,
0-
02
05
07
09
1:
0<
0=
0>
1?
#1165000000
b0001 "
b01110 #
b0001 %
b1110 (
1)
1-
1/
00
13
15
#1170000000
b0010 "
b01111 #
b0010 %
0'
b1111 (
0)
0*
0+
0-
0/
10
12
03
04
15
08
09
1:
0=
0>
1?
#1175000000
b0011 "
b10000 #
b0011 %
1'
b0000 (
1)
1*
1+
1-
1/
00
13
14
05
18
19
0:
1=
1>
0?
#1180000000
b0100 "
b10001 #
b0100 %
b0001 (
0)
0*
0-
0/
10
02
03
04
05
17
08
0:
#1185000000
b0101 "
b10010 #
b0101 %
b0010 (
1)
1-
1/
00
13
15
#1190000000
b0110 "
b10011 #
b0110 %
b0011 (
0)
0*
0-
0/
10
12
03
04
15
08
0:
#1195000000
b0111 "
b10100 #
b0111 %
b0100 (
1)
1*
1-
1/
00
13
14
05
18
1:
#1200000000
b1000 "
b10101 #
b1000 %
b0101 (
0)
0*
0+
0-
0/
10
02
03
04
05
07
08
09
1:
1<
0=
0?
#1205000000
b1001 "
b10110 #
b1001 %
b0110 (
1)
1-
1/
00
13
15
#1210000000
b1010 "
b10111 #
b1010 %
b0111 (
0)
0*
0+
0-
0/
10
12
03
04
15
08
09
1:
0=
0?
#1215000000
b1011 "
b11000 #
b1011 %
b1000 (
1)
1*
1+
1-
1/
00
13
14
05
18
19
0:
1=
1?
#1220000000
b1100 "
b11001 #
b1100 %
b1001 (
0)
0*
0-
0/
10
02
03
04
05
17
08
0:
#1225000000
b1101 "
b11010 #
b1101 %
b1010 (
1)
1-
1/
00
13
15
#1230000000
b1110 "
b11011 #
b1110 %
b1011 (
0)
0*
0-
0/
10
12
03
04
15
08
0:
#1235000000
b1111 "
b11100 #
b1111 %
b1100 (
1)
1*
1-
1/
00
13
14
05
18
1:
#1240000000
b1110 !
b0000 "
b01110 #
b1110 $
b0000 %
0'
b1110 (
0)
0*
0+
0,
0-
0/
11
02
03
04
15
07
08
09
1:
0<
0=
0>
1?
#1245000000
b0001 "
b01111 #
b0001 %
b1111 (
1-
10
#1250000000
b0010 "
b10000 #
b0010 %
1'
b0000 (
1*
1+
0-
00
12
14
05
18
19
0:
1=
1>
0?
#1255000000
b0011 "
b10001 #
b0011 %
b0001 (
1-
10
#1260000000
b0100 "
b10010 #
b0100 %
b0010 (
0*
0-
00
02
04
15
17
08
0:
#1265000000
b0101 "
b10011 #
b0101 %
b0011 (
1-
10
#1270000000
b0110 "
b10100 #
b0110 %
b0100 (
1*
0-
00
12
14
05
18
1:
#1275000000
b0111 "
b10101 #
b0111 %
b0101 (
1-
10
#1280000000
b1000 "
b10110 #
b1000 %
b0110 (
0*
0+
0-
00
02
04
15
07
08
09
1:
1<
0=
0?
#1285000000
b1001 "
b10111 #
b1001 %
b0111 (
1-
10
